setup.py
cakesAPI/__init__.py
cakesAPI.egg-info/PKG-INFO
cakesAPI.egg-info/SOURCES.txt
cakesAPI.egg-info/dependency_links.txt
cakesAPI.egg-info/requires.txt
cakesAPI.egg-info/top_level.txt
cakesAPI/api/__init__.py
cakesAPI/api/api_client.py
cakesAPI/api/api_request.py
cakesAPI/models/__init__.py
cakesAPI/models/cake.py
cakesAPI/models/recipe.py