Metadata-Version: 2.1
Name: cakesAPI
Version: 3.0
Summary: A Python library for interacting with cakes API
Home-page: https://git.e-science.pl/mursha213_dpp_2023/python_pip
Author: Murad Shahbazov
Author-email: 251213@student.pwr.edu.pl
